{
    "TelemetrySettings": {
        "TelemetryBatchSizeBytes": 16384,
        "TelemetryBatchIntervalInSecs": 15,
        "RefreshIntervalInSecs": 15,
        "DisableAll": false,
        "HeartBeatIntervalInMins": 30,
        "DebugMode": false,
        "SnapshotIntervalInMins": 60
    },
    "ManagedSettings": {
        "DncEndpointDns": "",
        "InfrastructureNetworkID": "",
        "NodeID": "",
        "NodeManagedIdentity": "",
        "DncTlsCertificateSubjectName": "dnc.azure.com",
        "NodeSyncIntervalInSeconds": 30
    },
    "HttpClientSettings": {
        "ConnectionTimeout": 5,
        "ResponseHeaderTimeout": 120
    },
    "ChannelMode": "Direct",
    "UseHTTPS" : false,
    "TLSSubjectName" : "",
    "TLSCertificatePath" : "",
    "TLSEndpoint" : "localhost:10091",
    "WireserverIP": "168.63.129.16"
}
